Workbook

Sheet Test Cases
A1: Test Case ID | B1: Module | C1: Test Case Title | D1: Description | E1: Preconditions | F1: Test Steps | G1: Test Data | H1: Expected Result | I1: Priority | J1: Test Type | K1: Automation Candidate | L1: Actual Result | M1: Status | N1: Remarks
A2: TC_DWS_001 | B2: Registration | C2: Register with valid details | D2: Verify a new user can register successfully with all mandatory fields filled correctly. | E2: User is not logged in. Email address has not been registered before. | F2: 1. Open https://demowebshop.tricentis.com/ 2. Click 'Register' in the header 3. Select Gender 'Male' 4. Enter First name, Last name, unique Email 5. Enter Password and the same value in Confirm password 6. Click 'Register' button 7. Click 'Continue' on the result page | G2: Email: <unique>@example.com | First: John | Last: Tester | Pwd: Test@1234 | H2: Message 'Your registration completed' is displayed. After Continue, user lands on home page and header shows the registered email with 'Log out' link. | I2: High | J2: Functional | K2: Yes | M2: Not Run
A3: TC_DWS_002 | B3: Registration | C3: Register with an already registered email | D3: Verify the system blocks registration when the email already exists. | E3: An account already exists for the email used. | F3: 1. Open https://demowebshop.tricentis.com/register 2. Fill all fields with valid values using an existing email 3. Click 'Register' | G3: Email: <already registered email> | Pwd: Test@1234 | H3: Registration fails with an error such as 'The specified email already exists'. No new account is created. | I3: High | J3: Negative | K3: Yes | M3: Not Run
A4: TC_DWS_003 | B4: Registration | C4: Mandatory field validation on empty registration form | D4: Verify validation messages for all mandatory fields when the form is submitted empty. | E4: User is on the Register page. | F4: 1. Open https://demowebshop.tricentis.com/register 2. Leave all fields blank 3. Click 'Register' | G4: All fields blank | H4: Validation messages appear for First name, Last name, Email, Password and Confirm password (e.g. 'First name is required.'). Form is not submitted. | I4: High | J4: Negative | K4: Yes | M4: Not Run
A5: TC_DWS_004 | B5: Registration | C5: Password and Confirm password mismatch | D5: Verify error is shown when Password and Confirm password do not match. | E5: User is on the Register page. | F5: 1. Open https://demowebshop.tricentis.com/register 2. Fill valid First name, Last name and unique Email 3. Enter Password 'Test@1234' and Confirm password 'Test@9999' 4. Click 'Register' | G5: Pwd: Test@1234 | Confirm: Test@9999 | H5: Error 'The password and confirmation password do not match.' is displayed. Registration is not completed. | I5: Medium | J5: Negative | K5: Yes | M5: Not Run
A6: TC_DWS_005 | B6: Registration | C6: Password shorter than minimum length | D6: Verify password length validation (minimum 6 characters). | E6: User is on the Register page. | F6: 1. Open https://demowebshop.tricentis.com/register 2. Fill valid First name, Last name and unique Email 3. Enter 5-character Password 'Ab@12' in both password fields 4. Click 'Register' | G6: Pwd: Ab@12 | H6: Error stating the password should have at least 6 characters is displayed. Registration is not completed. | I6: Medium | J6: Boundary | K6: Yes | M6: Not Run
A7: TC_DWS_006 | B7: Registration | C7: Invalid email format on registration | D7: Verify email format validation on the Register page. | E7: User is on the Register page. | F7: 1. Open https://demowebshop.tricentis.com/register 2. Enter valid First name and Last name 3. Enter Email 'abc.com' (no @ symbol) 4. Enter matching passwords 5. Click 'Register' | G7: Email: abc.com | H7: Error 'Wrong email' is displayed under the Email field. Registration is not completed. | I7: Medium | J7: Negative | K7: Yes | M7: Not Run
A8: TC_DWS_007 | B8: Login | C8: Login with valid credentials | D8: Verify a registered user can log in with correct email and password. | E8: A registered account exists. | F8: 1. Open https://demowebshop.tricentis.com/ 2. Click 'Log in' 3. Enter registered Email and Password 4. Click 'Log in' button | G8: Email: <registered email> | Pwd: Test@1234 | H8: User is logged in and redirected to home page. Header shows the user's email and 'Log out' link. | I8: High | J8: Functional | K8: Yes | M8: Not Run
A9: TC_DWS_008 | B9: Login | C9: Login with incorrect password | D9: Verify login fails when the password is wrong. | E9: A registered account exists. | F9: 1. Open https://demowebshop.tricentis.com/login 2. Enter registered Email 3. Enter an incorrect Password 4. Click 'Log in' | G9: Email: <registered email> | Pwd: Wrong@999 | H9: Message 'Login was unsuccessful. Please correct the errors and try again.' with 'The credentials provided are incorrect' is displayed. User remains logged out. | I9: High | J9: Negative | K9: Yes | M9: Not Run
A10: TC_DWS_009 | B10: Login | C10: Login with unregistered email | D10: Verify login fails for an email that has no account. | E10: Email is not registered. | F10: 1. Open https://demowebshop.tricentis.com/login 2. Enter an unregistered Email and any Password 3. Click 'Log in' | G10: Email: nouser_999@example.com | Pwd: Test@1234 | H10: Message 'Login was unsuccessful' with 'No customer account found' is displayed. User remains logged out. | I10: High | J10: Negative | K10: Yes | M10: Not Run
A11: TC_DWS_010 | B11: Login | C11: Login with empty fields | D11: Verify behaviour when the login form is submitted with blank Email and Password. | E11: User is on the Login page. | F11: 1. Open https://demowebshop.tricentis.com/login 2. Leave Email and Password blank 3. Click 'Log in' | G11: Blank | H11: Login is rejected with an error message (e.g. 'Login was unsuccessful. No customer account found'). User remains logged out. | I11: Medium | J11: Negative | K11: Yes | M11: Not Run
A12: TC_DWS_011 | B12: Login | C12: Logout from the application | D12: Verify a logged-in user can log out and the session ends. | E12: User is logged in. | F12: 1. Click 'Log out' in the header 2. Verify header links 3. Click browser Back button | G12: Registered credentials | H12: User is logged out. Header shows 'Register' and 'Log in' links. Using Back does not restore the logged-in state on account pages. | I12: High | J12: Functional | K12: Yes | M12: Not Run
A13: TC_DWS_012 | B13: Search | C13: Search with a valid keyword | D13: Verify products matching the keyword are listed. | E13: Home page is open. | F13: 1. Open https://demowebshop.tricentis.com/ 2. Type 'laptop' in the search box 3. Click 'Search' | G13: Keyword: laptop | H13: Search results page lists products whose name/description matches 'laptop' (e.g. 14.1-inch Laptop). | I13: High | J13: Functional | K13: Yes | M13: Not Run
... A51: TC_DWS_050 | B51: Community Poll | C51: Vote in the community poll | D51: Verify a user can vote in the home page community poll and see results. | E51: Home page is open. | F51: 1. Open https://demowebshop.tricentis.com/ 2. In the 'Community poll' block select an option (e.g. 'Good') 3. Click 'Vote' | G51: Poll option: Good | H51: Vote is recorded and poll results with percentages/vote counts are displayed in place of the voting options. Guest users may be asked to log in if the poll requires it. | I51: Low | J51: Functional | K51: Yes | M51: Not Run

Sheet Summary
A1: Demo Web Shop - Test Case Summary
A2: Application URL | B2: https://demowebshop.tricentis.com/
A3: Total Test Cases | B3: =COUNTA('Test Cases'!A2:A51) -> 50
A5: Module | B5: Count
A6: Registration | B6: =COUNTIF('Test Cases'!$B$2:$B$51,A6) -> 6
A7: Login | B7: =COUNTIF('Test Cases'!$B$2:$B$51,A7) -> 5
A8: Search | B8: =COUNTIF('Test Cases'!$B$2:$B$51,A8) -> 4
A9: Catalog | B9: =COUNTIF('Test Cases'!$B$2:$B$51,A9) -> 4
A10: Product Details | B10: =COUNTIF('Test Cases'!$B$2:$B$51,A10) -> 5
A11: Shopping Cart | B11: =COUNTIF('Test Cases'!$B$2:$B$51,A11) -> 8
A12: Wishlist | B12: =COUNTIF('Test Cases'!$B$2:$B$51,A12) -> 3
A13: Compare Products | B13: =COUNTIF('Test Cases'!$B$2:$B$51,A13) -> 1
A14: Currency | B14: =COUNTIF('Test Cases'!$B$2:$B$51,A14) -> 1
A15: Checkout | B15: =COUNTIF('Test Cases'!$B$2:$B$51,A15) -> 6
A16: My Account | B16: =COUNTIF('Test Cases'!$B$2:$B$51,A16) -> 2
A17: Newsletter | B17: =COUNTIF('Test Cases'!$B$2:$B$51,A17) -> 2
... A20: Community Poll | B20: =COUNTIF('Test Cases'!$B$2:$B$51,A20) -> 1
A22: Priority | B22: Count
A23: High | B23: =COUNTIF('Test Cases'!$I$2:$I$51,A23) -> 19
A24: Medium | B24: =COUNTIF('Test Cases'!$I$2:$I$51,A24) -> 21
A25: Low | B25: =COUNTIF('Test Cases'!$I$2:$I$51,A25) -> 10
A27: Test Type | B27: Count
A28: Functional | B28: =COUNTIF('Test Cases'!$J$2:$J$51,A28) -> 28
A29: Negative | B29: =COUNTIF('Test Cases'!$J$2:$J$51,A29) -> 14
A30: Boundary | B30: =COUNTIF('Test Cases'!$J$2:$J$51,A30) -> 3
A31: UI | B31: =COUNTIF('Test Cases'!$J$2:$J$51,A31) -> 3
A32: End-to-End | B32: =COUNTIF('Test Cases'!$J$2:$J$51,A32) -> 2
A34: Execution Status | B34: Count
A35: Not Run | B35: =COUNTIF('Test Cases'!$M$2:$M$51,A35) -> 50
A36: Pass | B36: =COUNTIF('Test Cases'!$M$2:$M$51,A36) -> 0
A37: Fail | B37: =COUNTIF('Test Cases'!$M$2:$M$51,A37) -> 0
A38: Blocked | B38: =COUNTIF('Test Cases'!$M$2:$M$51,A38) -> 0
A39: Skipped | B39: =COUNTIF('Test Cases'!$M$2:$M$51,A39) -> 0
A41: Note: Test data uses placeholder values; replace <unique> / <registered email> with real values at execution. Exact message wording may vary slightly on the live site.
